selfupdate/__init__.py
selfupdate-0.2.0.dist-info/LICENSE
selfupdate-0.2.0.dist-info/METADATA
selfupdate-0.2.0.dist-info/WHEEL
selfupdate-0.2.0.dist-info/top_level.txt
selfupdate-0.2.0.dist-info/RECORD
